{
  "symbol": "KBE",
  "holdings": [
    {
      "symbol": "VOYA",
      "weight": 0.011410001
    },
    {
      "symbol": "APO",
      "weight": 0.011195901
    },
    {
      "symbol": "FBP",
      "weight": 0.011070699
    },
    {
      "symbol": "EWBC",
      "weight": 0.0110426
    },
    {
      "symbol": "TFIN",
      "weight": 0.0109385
    },
    {
      "symbol": "NTRS",
      "weight": 0.0108947
    },
    {
      "symbol": "CATY",
      "weight": 0.0108311
    },
    {
      "symbol": "CRBG",
      "weight": 0.0108244
    },
    {
      "symbol": "C",
      "weight": 0.0108168
    },
    {
      "symbol": "WAL",
      "weight": 0.0108117
    }
  ]
}