{
  "symbol": "RSPR",
  "holdings": [
    {
      "symbol": "SBAC",
      "weight": 0.036414698
    },
    {
      "symbol": "IRM",
      "weight": 0.0363498
    },
    {
      "symbol": "INVH",
      "weight": 0.0354244
    },
    {
      "symbol": "BXP",
      "weight": 0.0347969
    },
    {
      "symbol": "DLR",
      "weight": 0.0345397
    },
    {
      "symbol": "EQIX",
      "weight": 0.0345298
    },
    {
      "symbol": "HST",
      "weight": 0.0341793
    },
    {
      "symbol": "EQR",
      "weight": 0.0337352
    },
    {
      "symbol": "CBRE",
      "weight": 0.0334393
    },
    {
      "symbol": "SPG",
      "weight": 0.0333592
    }
  ]
}